cherrypy_jinja2/__init__.py
cherrypy_jinja2-2.2.dist-info/LICENSE
cherrypy_jinja2-2.2.dist-info/METADATA
cherrypy_jinja2-2.2.dist-info/WHEEL
cherrypy_jinja2-2.2.dist-info/top_level.txt
cherrypy_jinja2-2.2.dist-info/RECORD
