Metadata-Version: 2.1
Name: cherrypy-jinja2
Version: 2.2
Summary: CherryPy tool to render output through Jinja2 templates
Author: Graham Clinch
Author-email: g.clinch@lancaster.ac.uk
Classifier: Development Status :: 5 - Production/Stable
Classifier: Framework :: CherryPy
Classifier: License :: OSI Approved :: Apache Software License
License-File: LICENSE
Requires-Dist: CherryPy
Requires-Dist: Jinja2
